stellanow_api_internals/__init__.py
stellanow_api_internals/auth/__init__.py
stellanow_api_internals/auth/keycloak_auth.py
stellanow_api_internals/clients/__init__.py
stellanow_api_internals/clients/base_api_client.py
stellanow_api_internals/clients/notification_config_client.py
stellanow_api_internals/clients/workflow_manager_client.py
stellanow_api_internals/core/__init__.py
stellanow_api_internals/core/enums.py
stellanow_api_internals/core/helpers.py
stellanow_api_internals/datatypes/__init__.py
stellanow_api_internals/datatypes/core.py
stellanow_api_internals/datatypes/notification_config.py
stellanow_api_internals/datatypes/workflow_mgmt.py
stellanow_api_internals/exceptions/__init__.py
stellanow_api_internals/exceptions/api_exceptions.py
stellanow_api_internals-0.0.5.dist-info/METADATA
stellanow_api_internals-0.0.5.dist-info/WHEEL
stellanow_api_internals-0.0.5.dist-info/RECORD
