Metadata-Version: 2.3
Name: stellanow-api-internals
Version: 0.0.5
Summary: Library for communicating with the internal API of StellaNow platform.
Author: Stella Technologies (UK) Limited
Requires-Python: >=3.11,<4.0
Classifier: Programming Language :: Python :: 3
Classifier: Programming Language :: Python :: 3.11
Classifier: Programming Language :: Python :: 3.12
Classifier: Programming Language :: Python :: 3.13
Requires-Dist: beautifulsoup4 (>=4.13.3,<5.0.0)
Requires-Dist: httpx (>=0.28.1,<0.29.0)
Requires-Dist: loguru (>=0.7,<1.0)
Requires-Dist: pydantic (>=2.10.6,<3.0.0)
Requires-Dist: python-keycloak (>=5.3.1,<6.0.0)
